grexx_gcloudtools/__init__.py
grexx_gcloudtools/authentication.py
grexx_gcloudtools/bigquery.py
grexx_gcloudtools/cloud_ml.py
grexx_gcloudtools/log.py
grexx_gcloudtools/storage.py
grexx_gcloudtools-0.0.2.dist-info/METADATA
grexx_gcloudtools-0.0.2.dist-info/WHEEL
grexx_gcloudtools-0.0.2.dist-info/top_level.txt
grexx_gcloudtools-0.0.2.dist-info/RECORD
