Metadata-Version: 2.1
Name: grexx-gcloudtools
Version: 0.0.2
Summary: Tools for accessing Google Cloud interfaces for Budget Coach services
Home-page: UNKNOWN
Author: Grexx
Author-email: servicedesk@grexx.net
License: UNKNOWN
Platform: UNKNOWN
Classifier: Programming Language :: Python :: 3
Classifier: Programming Language :: Python :: 3.7
Requires-Dist: click
Requires-Dist: tqdm
Requires-Dist: google-cloud-core
Requires-Dist: google-cloud-bigquery
Requires-Dist: google-cloud-storage
Requires-Dist: google-cloud-tasks
Requires-Dist: google-api-core
Requires-Dist: google-api-python-client
Requires-Dist: google-auth
Requires-Dist: google-auth-httplib2
Requires-Dist: flask
Requires-Dist: Flask-Restful
Requires-Dist: pyarrow
